anodot/__init__.py
anodot/api_client.py
anodot/metric.py
anodot/tools.py
python_anodot-2.0.7.dist-info/LICENSE
python_anodot-2.0.7.dist-info/METADATA
python_anodot-2.0.7.dist-info/WHEEL
python_anodot-2.0.7.dist-info/top_level.txt
python_anodot-2.0.7.dist-info/RECORD
