Metadata-Version: 2.1
Name: python-anodot
Version: 2.0.7
Summary: Anodot API python package
Home-page: https://github.com/anodot/anodot-python
Author: Anodot
License: MIT
Classifier: License :: OSI Approved :: MIT License
Classifier: Programming Language :: Python :: 3
Classifier: Programming Language :: Python :: 3.7
Classifier: Programming Language :: Python :: 3.8
Classifier: Programming Language :: Python :: 3.9
Classifier: Programming Language :: Python :: 3.10
License-File: LICENSE
Requires-Dist: requests
